hello_world_prod_vk_2/__init__.py
hello_world_prod_vk_2/main.py
hello_world_prod_vk_2-0.2.1.dist-info/LICENSE
hello_world_prod_vk_2-0.2.1.dist-info/METADATA
hello_world_prod_vk_2-0.2.1.dist-info/WHEEL
hello_world_prod_vk_2-0.2.1.dist-info/top_level.txt
hello_world_prod_vk_2-0.2.1.dist-info/RECORD
